ThreeBodyProblem/__init__.py
ThreeBodyProblem/train.py
ThreeBodyProblem/train_paral.py
ThreeBodyProblem/RL_agent/__init__.py
ThreeBodyProblem/RL_agent/generate_system_json.py
ThreeBodyProblem/RL_agent/model.py
ThreeBodyProblem/env/__init__.py
ThreeBodyProblem/env/batch_quicksim.py
ThreeBodyProblem/env/fast_sim.py
ThreeBodyProblem/env/three_body_gym.py
ThreeBodyProblem/env/three_body_vectorized.py
polysolaris/__init__.py
system_simulation/__init__.py
system_simulation/body.py
system_simulation/loadplanets.py
system_simulation/main.py
system_simulation/simulation.py
system_simulation/solar_system.py
system_simulation/solar_system_demo.py
system_simulation/system_collision_demo.py
system_simulation/vector.py
system_simulation/data/3_body.json
system_simulation/data/custom_system.json
system_simulation/data/death_spiral.json
system_simulation/data/figure_8.json
system_simulation/data/planets.json
system_simulation/data/predicted_system.json
system_simulation/data/solar_system.json
system_simulation/data/solar_system2.json
system_simulation/data/test.json
polysolaris-0.1.1.dist-info/METADATA
polysolaris-0.1.1.dist-info/WHEEL
polysolaris-0.1.1.dist-info/entry_points.txt
polysolaris-0.1.1.dist-info/top_level.txt
polysolaris-0.1.1.dist-info/RECORD
