Metadata-Version: 2.4
Name: polysolaris
Version: 0.1.1
Summary: A 3D N-body gravity simulation
Requires-Python: >=3.8
Requires-Dist: matplotlib
Requires-Dist: imageio-ffmpeg
Requires-Dist: imageio
Requires-Dist: torch
Requires-Dist: gymnasium
Requires-Dist: numpy
